LICENSE
README.md
setup.py
cad/__init__.py
cad/pipe.py
cad/sample_image.py
cad/test.py
cad/train.py
cad/validate.py
cad/__pycache__/__init__.cpython-310.pyc
cad/__pycache__/__init__.cpython-311.pyc
cad/__pycache__/pipe.cpython-310.pyc
cad/__pycache__/pipe.cpython-311.pyc
cad/callbacks/__init__.py
cad/callbacks/checkpoint_and_validate.py
cad/callbacks/data.py
cad/callbacks/ema.py
cad/callbacks/fix_nans.py
cad/callbacks/log_images.py
cad/callbacks/__pycache__/__init__.cpython-310.pyc
cad/callbacks/__pycache__/checkpoint_and_validate.cpython-310.pyc
cad/callbacks/__pycache__/data.cpython-310.pyc
cad/callbacks/__pycache__/ema.cpython-310.pyc
cad/callbacks/__pycache__/fid.cpython-310.pyc
cad/callbacks/__pycache__/fix_nans.cpython-310.pyc
cad/callbacks/__pycache__/log_images.cpython-310.pyc
cad/configs/config.yaml
cad/configs/computer/a100.yaml
cad/configs/computer/cluster-node-a100.yaml
cad/configs/computer/cluster-node-a100_fsdp.yaml
cad/configs/computer/cluster-node-v100.yaml
cad/configs/computer/cpu.yaml
cad/configs/computer/v100.yaml
cad/configs/data/default.yaml
cad/configs/data/webdataset.yaml
cad/configs/data/collate_fn/default.yaml
cad/configs/data/collate_fn/from_dict_pad.yaml
cad/configs/data/collate_fn/from_tuple.yaml
cad/configs/data/dataset/cc12m.yaml
cad/configs/data/dataset/cc12m_la6.yaml
cad/configs/data/dataset/cc3m.yaml
cad/configs/data/dataset/cifar10.yaml
cad/configs/data/dataset/imagenet.yaml
cad/configs/data/dataset/imagenet_ldm.yaml
cad/configs/data/dataset/imagenet_ldm_text.yaml
cad/configs/data/train_aug/center_crop.yaml
cad/configs/data/train_aug/none.yaml
cad/configs/data/val_aug/center_crop.yaml
cad/configs/data/val_aug/none.yaml
cad/configs/model/cad_text_cond.yaml
cad/configs/model/class_cond.yaml
cad/configs/model/text_cond.yaml
cad/configs/model/cond_preprocessing/label.yaml
cad/configs/model/cond_preprocessing/precomputed_text_emb.yaml
cad/configs/model/cond_preprocessing/text.yaml
cad/configs/model/data_preprocessing/pixels.yaml
cad_diffusion.egg-info/PKG-INFO
cad_diffusion.egg-info/SOURCES.txt
cad_diffusion.egg-info/dependency_links.txt
cad_diffusion.egg-info/requires.txt
cad_diffusion.egg-info/top_level.txt